coinaddrng/__init__.py
coinaddrng/base.py
coinaddrng/currency.py
coinaddrng/interfaces.py
coinaddrng/validation.py
tests/__init__.py
tests/test_coinaddr.py
tests/test_currency.py
tests/test_validation.py
coinaddrng-1.1.2.dist-info/LICENSE
coinaddrng-1.1.2.dist-info/METADATA
coinaddrng-1.1.2.dist-info/WHEEL
coinaddrng-1.1.2.dist-info/top_level.txt
coinaddrng-1.1.2.dist-info/RECORD
